sphinxcontrib_adadomain-0.2-py3.6-nspkg.pth
sphinxcontrib/adadomain.py
sphinxcontrib_adadomain-0.2.dist-info/DESCRIPTION.rst
sphinxcontrib_adadomain-0.2.dist-info/METADATA
sphinxcontrib_adadomain-0.2.dist-info/RECORD
sphinxcontrib_adadomain-0.2.dist-info/WHEEL
sphinxcontrib_adadomain-0.2.dist-info/metadata.json
sphinxcontrib_adadomain-0.2.dist-info/namespace_packages.txt
sphinxcontrib_adadomain-0.2.dist-info/top_level.txt
