Metadata-Version: 2.0
Name: sphinxcontrib-adadomain
Version: 0.2
Summary: Sphinx "adadomain" extension
Home-page: http://bitbucket.org/tkoskine/sphinxcontrib-adadomain
Author: Tero Koskinen
Author-email: tero.koskinen@iki.fi
License: BSD
Download-URL: http://pypi.python.org/pypi/sphinxcontrib-adadomain
Platform: any
Classifier: Development Status :: 4 - Beta
Classifier: Environment :: Console
Classifier: Environment :: Web Environment
Classifier: Intended Audience :: Developers
Classifier: License :: OSI Approved :: BSD License
Classifier: Operating System :: OS Independent
Classifier: Programming Language :: Python
Classifier: Topic :: Documentation
Classifier: Topic :: Utilities
Requires-Dist: Sphinx (>=1.0)
